LICENSE
MANIFEST.in
README.md
setup.cfg
setup.py
scikit_XCS.egg-info/PKG-INFO
scikit_XCS.egg-info/SOURCES.txt
scikit_XCS.egg-info/dependency_links.txt
scikit_XCS.egg-info/requires.txt
scikit_XCS.egg-info/top_level.txt
skXCS/Classifier.py
skXCS/ClassifierSet.py
skXCS/DataManagement.py
skXCS/Environment.py
skXCS/IterationRecord.py
skXCS/PredictionArray.py
skXCS/StringEnumerator.py
skXCS/Timer.py
skXCS/XCS.py
skXCS/__init__.py
test/__init__.py
test/test_StringEnumerator.py
test/test_XCS.py
test/DataSets/Real/ContinuousAndNonBinaryDiscreteAttributes.csv
test/DataSets/Real/ContinuousAndNonBinaryDiscreteAttributesMissing.csv
test/DataSets/Real/MulticlassPhenotype.csv
test/DataSets/Real/Multiplexer11.csv
test/DataSets/Real/Multiplexer11Modified.csv
test/DataSets/Real/Multiplexer20.csv
test/DataSets/Real/Multiplexer20Modified.csv
test/DataSets/Real/Multiplexer6.csv
test/DataSets/Real/Multiplexer6Modified.csv
test/DataSets/Tests/ContinuousPhenotype.csv
test/DataSets/Tests/MissingFeatureAndPhenotypeData.csv
test/DataSets/Tests/MissingFeatureData.csv
test/DataSets/Tests/StringData.csv
test/DataSets/Tests/StringData2.csv
test/DataSets/Tests/NumericTests/numericFloats.csv
test/DataSets/Tests/NumericTests/numericFloatsMissing.csv
test/DataSets/Tests/NumericTests/numericFloatsNAN.csv
test/DataSets/Tests/NumericTests/numericFloatsString.csv
test/DataSets/Tests/NumericTests/numericInts.csv
test/DataSets/Tests/SpecificityTests/Specifics.csv